ovos_wikipedia_solver/__init__.py
ovos_wikipedia_solver/version.py
ovos_wikipedia_solver-0.1.2.dist-info/METADATA
ovos_wikipedia_solver-0.1.2.dist-info/WHEEL
ovos_wikipedia_solver-0.1.2.dist-info/entry_points.txt
ovos_wikipedia_solver-0.1.2.dist-info/top_level.txt
ovos_wikipedia_solver-0.1.2.dist-info/RECORD
