Metadata-Version: 2.4
Name: ovos_wikipedia_solver
Version: 0.1.2
Summary: ovos wikipedia plugin
Home-page: https://github.com/OpenVoiceOS/ovos-solver-wikipedia-plugin
Author: JarbasAi
Author-email: jarbasai@mailfence.com
License: Apache-2.0
Keywords: ovos skill plugin
Requires-Dist: ovos-utils<1.0.0,>=0.7.0
Requires-Dist: ovos-plugin-manager<3.0.0,>=0.0.26
Requires-Dist: ovos-bus-client>=1.0.1
Requires-Dist: ovos-solver-bm25-plugin<1.0.0,>=0.0.1
Requires-Dist: crf_query_xtract<1.0.0,>=0.1.2
Requires-Dist: brill_postagger<1.0.0,>=0.1.2
Dynamic: author
Dynamic: author-email
Dynamic: description
Dynamic: description-content-type
Dynamic: home-page
Dynamic: keywords
Dynamic: license
Dynamic: requires-dist
Dynamic: summary
